impresso_pipelines/__init__.py
impresso_pipelines/adclassifier/__init__.py
impresso_pipelines/adclassifier/adclassifier_pipeline.py
impresso_pipelines/langident/__init__.py
impresso_pipelines/langident/langident_pipeline.py
impresso_pipelines/ldatopics/SPACY.py
impresso_pipelines/ldatopics/__init__.py
impresso_pipelines/ldatopics/config.py
impresso_pipelines/ldatopics/input_reader.py
impresso_pipelines/ldatopics/language_inferencer.py
impresso_pipelines/ldatopics/mallet2topic_assignment_jsonl.py
impresso_pipelines/ldatopics/mallet_pipeline.py
impresso_pipelines/ldatopics/mallet_topic_inferencer.py
impresso_pipelines/ldatopics/mallet_vectorizer_changed.py
impresso_pipelines/ldatopics/s3_to_local_stamps.py
impresso_pipelines/newsagencies/README.md
impresso_pipelines/newsagencies/__init__.py
impresso_pipelines/newsagencies/config.py
impresso_pipelines/newsagencies/newsagencies_pipeline.py
impresso_pipelines/ocrqa/__init__.py
impresso_pipelines/ocrqa/ocrqa_pipeline.py
impresso_pipelines/solrnormalization/__init__.py
impresso_pipelines/solrnormalization/lang_configs.py
impresso_pipelines/solrnormalization/solrnormalization_pipeline.py
impresso_pipelines/solrnormalization/stopwords_de.txt
impresso_pipelines/solrnormalization/stopwords_en.txt
impresso_pipelines/solrnormalization/stopwords_es.txt
impresso_pipelines/solrnormalization/stopwords_fr.txt
impresso_pipelines/solrnormalization/stopwords_it.txt
impresso_pipelines/solrnormalization/stopwords_nl.txt
impresso_pipelines/solrnormalization/stopwords_pt.txt
impresso_pipelines-0.6.0.1.dist-info/METADATA
impresso_pipelines-0.6.0.1.dist-info/WHEEL
impresso_pipelines-0.6.0.1.dist-info/RECORD
