Metadata-Version: 2.1
Name: impresso-pipelines
Version: 0.6.0.1
Summary: A custom package containing multiple pipelines simplifying reproducibility of impresso steps
Author: Glebs Vinarskis
Author-email: gleb.vinarskis@gmail.com
Requires-Python: >=3.11,<3.13
Classifier: Programming Language :: Python :: 3
Classifier: Programming Language :: Python :: 3.11
Provides-Extra: adclassifier
Provides-Extra: all
Provides-Extra: langident
Provides-Extra: ldatopics
Provides-Extra: newsagencies
Provides-Extra: ocrqa
Provides-Extra: solrnormalization
Requires-Dist: boto3 (>=1.35,<1.36) ; extra == "ldatopics" or extra == "all"
Requires-Dist: cython
Requires-Dist: floret ; extra == "langident" or extra == "ocrqa" or extra == "ldatopics" or extra == "solrnormalization" or extra == "all"
Requires-Dist: huggingface_hub ; extra == "langident" or extra == "ocrqa" or extra == "ldatopics" or extra == "solrnormalization" or extra == "all"
Requires-Dist: jpype1 (>=1.6,<1.7) ; extra == "ldatopics" or extra == "solrnormalization" or extra == "all"
Requires-Dist: jsonschema (>=4.23,<4.24) ; extra == "ldatopics" or extra == "all"
Requires-Dist: numpy (>=1.26,<1.27)
Requires-Dist: pybloomfilter3 ; extra == "ocrqa" or extra == "all"
Requires-Dist: pysolr ; extra == "solrnormalization"
Requires-Dist: python-dotenv (>=1.0,<1.1) ; extra == "ldatopics" or extra == "all"
Requires-Dist: smart_open (>=6.3,<6.4) ; extra == "ldatopics" or extra == "all"
Requires-Dist: spacy (>=3.7,<3.8) ; extra == "ldatopics" or extra == "all"
Requires-Dist: torch (>=2.3,<2.4) ; extra == "newsagencies" or extra == "adclassifier" or extra == "all"
Requires-Dist: torchvision (>=0.18,<0.19) ; extra == "newsagencies"
Requires-Dist: transformers (>=4.49,<4.50) ; extra == "newsagencies" or extra == "adclassifier" or extra == "all"
Project-URL: homepage, https://github.com/impresso/impresso-pipelines
